odoo/addons/account_bank_statement_clear_partner/README.rst
odoo/addons/account_bank_statement_clear_partner/__init__.py
odoo/addons/account_bank_statement_clear_partner/__manifest__.py
odoo/addons/account_bank_statement_clear_partner/i18n/account_bank_statement_clear_partner.pot
odoo/addons/account_bank_statement_clear_partner/i18n/nl.po
odoo/addons/account_bank_statement_clear_partner/models/__init__.py
odoo/addons/account_bank_statement_clear_partner/models/account_bank_statement.py
odoo/addons/account_bank_statement_clear_partner/readme/CONFIGURE.rst
odoo/addons/account_bank_statement_clear_partner/readme/CONTRIBUTORS.rst
odoo/addons/account_bank_statement_clear_partner/readme/DESCRIPTION.rst
odoo/addons/account_bank_statement_clear_partner/readme/USAGE.rst
odoo/addons/account_bank_statement_clear_partner/static/description/icon.png
odoo/addons/account_bank_statement_clear_partner/static/description/index.html
odoo/addons/account_bank_statement_clear_partner/tests/__init__.py
odoo/addons/account_bank_statement_clear_partner/tests/test_account_bank_statement_clear_patner.py
odoo/addons/account_bank_statement_clear_partner/views/account_bank_statement_views.xml
odoo13_addon_account_bank_statement_clear_partner-13.0.1.0.1.dev4.dist-info/METADATA
odoo13_addon_account_bank_statement_clear_partner-13.0.1.0.1.dev4.dist-info/WHEEL
odoo13_addon_account_bank_statement_clear_partner-13.0.1.0.1.dev4.dist-info/top_level.txt
odoo13_addon_account_bank_statement_clear_partner-13.0.1.0.1.dev4.dist-info/RECORD
